vendor_files/__init__.py
vendor_files/models.py
vendor_files/management/__init__.py
vendor_files/management/commands/__init__.py
vendor_files/management/commands/download_vendor_files.py
vendor_files/templatetags/__init__.py
vendor_files/templatetags/vendor_tags.py
django_vendor_files-0.3.dist-info/METADATA
django_vendor_files-0.3.dist-info/WHEEL
django_vendor_files-0.3.dist-info/top_level.txt
django_vendor_files-0.3.dist-info/RECORD
