Metadata-Version: 2.1
Name: django-vendor-files
Version: 0.3
Summary: A small extension to download css and js vendor files from CDNs and host them locally.
Home-page: https://github.com/aipescience/django-vendor-files
Author: Jochen Klar
Author-email: mail@jochenklar.de
Maintainer: Jochen Klar
Maintainer-email: mail@jochenklar.de
License: Apache-2.0
Platform: UNKNOWN
Classifier: Environment :: Web Environment
Classifier: Framework :: Django
Classifier: License :: OSI Approved :: Apache Software License
Classifier: Operating System :: OS Independent
Classifier: Programming Language :: Python :: 2.7
Classifier: Programming Language :: Python :: 3.4
Classifier: Programming Language :: Python :: 3.5
Classifier: Programming Language :: Python :: 3.6
Requires-Dist: Django (>=1.11)
Requires-Dist: requests
